india_stocks_api/__init__.py
india_stocks_api/utils.py
india_stocks_api/brokers/__init__.py
india_stocks_api/brokers/angelone.py
india_stocks_api/brokers/base/__init__.py
india_stocks_api/brokers/base/broker.py
india_stocks_api/brokers/base/constants.py
india_stocks_api/brokers/base/errors.py
india_stocks_api/config/__init__.py
india_stocks_api/config/network.py
india_stocks_api/database/__init__.py
india_stocks_api/database/migrations/__init__.py
india_stocks_api/database/migrations/migration_manager.py
india_stocks_api/database/models/__init__.py
india_stocks_api/database/models/base.py
india_stocks_api/database/models/broker_instrument.py
india_stocks_api/database/models/enums.py
india_stocks_api/database/models/exchange.py
india_stocks_api/database/models/instrument.py
india_stocks_api/database/providers/__init__.py
india_stocks_api/database/providers/angelone_provider.py
india_stocks_api/database/providers/base_provider.py
india_stocks_api/database/services/__init__.py
india_stocks_api/database/services/instrument_service.py
india_stocks_api/database/services/instrument_store.py
india_stocks_api/database/utils/__init__.py
india_stocks_api/database/utils/db_utils.py
india_stocks_api/utils/__init__.py
india_stocks_api/utils/cache_utils.py
india_stocks_api/utils/common.py
india_stocks_api-1.0.0.dist-info/licenses/LICENSE
scripts/__init__.py
scripts/setup_database.py
scripts/sync_angelone_data.py
scripts/test_angelone_integration.py
india_stocks_api-1.0.0.dist-info/METADATA
india_stocks_api-1.0.0.dist-info/WHEEL
india_stocks_api-1.0.0.dist-info/top_level.txt
india_stocks_api-1.0.0.dist-info/RECORD
